msopt2/__init__.py
msopt2/api.cpython-311-darwin.so
msopt2/api.cpython-311-x86_64-linux-gnu.so
msopt2/conflict.cpython-311-darwin.so
msopt2/conflict.cpython-311-x86_64-linux-gnu.so
msopt2/entities.cpython-311-darwin.so
msopt2/entities.cpython-311-x86_64-linux-gnu.so
msopt2/envr.cpython-311-darwin.so
msopt2/envr.cpython-311-x86_64-linux-gnu.so
msopt2/licgen.cpython-311-darwin.so
msopt2/licgen.cpython-311-x86_64-linux-gnu.so
msopt2-0.0.1.dist-info/METADATA
msopt2-0.0.1.dist-info/WHEEL
msopt2-0.0.1.dist-info/RECORD
